external_github_contributors/__init__.py
external_github_contributors/__main__.py
external_github_contributors-1.1.1.dist-info/LICENSE
external_github_contributors-1.1.1.dist-info/METADATA
external_github_contributors-1.1.1.dist-info/WHEEL
external_github_contributors-1.1.1.dist-info/entry_points.txt
external_github_contributors-1.1.1.dist-info/RECORD
