Metadata-Version: 2.1
Name: external-github-contributors
Version: 1.1.1
Summary: Simple script to list external contributors to a project who authored contributions between two specific references
Author: Brendan Abolivier
Author-email: hello@brendanabolivier.com
Requires-Python: >=3.10,<4.0
Classifier: Programming Language :: Python :: 3
Classifier: Programming Language :: Python :: 3.10
Classifier: Programming Language :: Python :: 3.11
Requires-Dist: requests (>=2.28.1,<3.0.0)
